hamsunwoo_cmd/__init__.py
hamsunwoo_cmd/cmd.py
hamsunwoo_cmd-0.1.1.dist-info/METADATA
hamsunwoo_cmd-0.1.1.dist-info/WHEEL
hamsunwoo_cmd-0.1.1.dist-info/entry_points.txt
hamsunwoo_cmd-0.1.1.dist-info/top_level.txt
hamsunwoo_cmd-0.1.1.dist-info/RECORD
