Metadata-Version: 2.1
Name: hamsunwoo_cmd
Version: 0.1.1
Summary: Default template for PDM package
Author-email: sunwoo <summerham22@gmail.com>
License: MIT
Requires-Python: >=3.9
Requires-Dist: hamsunwoo-lotto >=0.2.0
